bubbleconf/__init__.py
bubbleconf/config_annotation.py
bubbleconf/parsers/__init__.py
bubbleconf/parsers/cli_parser.py
bubbleconf/parsers/config_error.py
bubbleconf/parsers/env_parser.py
bubbleconf/parsers/parse_priority.py
bubbleconf-0.1.3.dist-info/licenses/LICENSE
bubbleconf-0.1.3.dist-info/METADATA
bubbleconf-0.1.3.dist-info/WHEEL
bubbleconf-0.1.3.dist-info/top_level.txt
bubbleconf-0.1.3.dist-info/RECORD
