Metadata-Version: 2.4
Name: bubbleconf
Version: 0.1.3
Summary: A python package for reading configurations from different sources
Author-email: Felix Bjært Hargreaves <not-a-real@email.com>
License: MIT License
Project-URL: Homepage, https://github.com/bubbleconf/
Project-URL: Repository, https://github.com/bubbleconf/bubbleconf
Classifier: Development Status :: 3 - Alpha
Classifier: Programming Language :: Python :: 3
Classifier: Programming Language :: Python :: 3 :: Only
Classifier: License :: OSI Approved :: MIT License
Requires-Python: >=3.10
License-File: LICENSE
Dynamic: license-file
